clishow.py
clishow-1.0.dist-info/METADATA
clishow-1.0.dist-info/WHEEL
clishow-1.0.dist-info/entry_points.txt
clishow-1.0.dist-info/top_level.txt
clishow-1.0.dist-info/RECORD
