Metadata-Version: 2.1
Name: clishow
Version: 1.0
Home-page: https://github.com/kojunseo/cli-show
Author: Junseo Ko
Author-email: kojunseo@icloud.com
Requires-Dist: opencv-python
Requires-Dist: matplotlib
Requires-Dist: numpy
Requires-Dist: wave
